neuron0.1/mac.sv
module mac (
	input logic	clk,  			//27MHz
	input logic	reset,			//lever to clean memory
	input logic signed [7:0] data_in,	//8-bit
	input logic signed [7:0] weight, 	//8-bit
	output logic signed [15:0] sum_out //16 bit running total
	);

	//Block triggered only when clock ticks up (posedge)
	always_ff @(posedge clk) begin
		if (reset) begin
			sum_out <= 0;
		end else begin
			sum_out <= sum_out + (data_in * weight);
		end
	end
endmodule

neuron0.1/waveform.vcd
$version Generated by VerilatedVcd $end
$timescale 1s $end
 $scope module TOP $end
  $var wire 1 " clk $end
  $var wire 1 # reset $end
  $var wire 8 $ data_in [7:0] $end
  $var wire 8 % weight [7:0] $end
  $var wire 16 & sum_out [15:0] $end
  $scope module mac $end
   $var wire 1 " clk $end
   $var wire 1 # reset $end
   $var wire 8 $ data_in [7:0] $end
   $var wire 8 % weight [7:0] $end
   $var wire 16 & sum_out [15:0] $end
  $upscope $end
 $upscope $end
$enddefinitions $end


#0
0"
1#
b00000000 $
b00000000 %
b0000000000000000 &
#1
1"
#2
0"
#3
1"
#4
0"
#5
1"
0#
b00000101 $
b00000010 %
b0000000000001010 &
#6
0"
#7
1"
b0000000000010100 &
#8
0"
#9
1"
b0000000000011110 &
#10
0"
#11
1"
b0000000000101000 &
#12
0"
#13
1"
b0000000000110010 &
#14
0"
#15
1"
b0000000000111100 &
#16
0"
#17
1"
b0000000001000110 &
#18
0"
#19
1"
b0000000001010000 &
#20
0"
#21
1"
b11111101 $
b00000011 %
b0000000001000111 &
#22
0"
#23
1"
b0000000000111110 &
#24
0"
#25
1"
b0000000000110101 &
#26
0"
#27
1"
b0000000000101100 &
#28
0"
#29
1"
b0000000000100011 &
#30
0"
#31
1"
b0000000000011010 &
#32
0"
#33
1"
b0000000000010001 &
#34
0"
#35
1"
b0000000000001000 &
